sophia_doc/__init__.py
sophia_doc/__main__.py
sophia_doc/py.typed
sophia_doc/utils.py
sophia_doc/builders/__init__.py
sophia_doc/builders/markdown.py
sophia_doc-0.1.9.dist-info/METADATA
sophia_doc-0.1.9.dist-info/WHEEL
sophia_doc-0.1.9.dist-info/entry_points.txt
sophia_doc-0.1.9.dist-info/licenses/LICENSE
sophia_doc-0.1.9.dist-info/RECORD
