Metadata-Version: 2.4
Name: sophia-doc
Version: 0.1.9
Summary: A python package to automatically generate API documents for Python modules.
Project-URL: Homepage, https://github.com/st1020/sophia-doc
Project-URL: Source, https://github.com/st1020/sophia-doc
Author-email: st1020 <me@st1020.com>
License: MIT
License-File: LICENSE
Keywords: doc,documentation,markdown,pydoc,sophia-doc
Classifier: Development Status :: 3 - Alpha
Classifier: License :: OSI Approved :: MIT License
Classifier: Operating System :: OS Independent
Classifier: Programming Language :: Python :: 3
Classifier: Topic :: Documentation
Classifier: Topic :: Software Development
Classifier: Topic :: Software Development :: Documentation
Classifier: Topic :: Text Processing
Classifier: Topic :: Text Processing :: Markup
Classifier: Topic :: Utilities
Requires-Python: >=3.9
Requires-Dist: docstring-parser>=0.16
Requires-Dist: typing-extensions>=4.7.1
